{"attributes": {"packageName": "", "fullName": "", "hasWarning": true, "name": ""}, "type": "doctree", "children": [{"type": "packages", "children": [{"attributes": {"packageName": "", "fullName": "qx", "name": "qx"}, "type": "package", "children": [{"type": "packages", "children": [{"attributes": {"packageName": "qx", "fullName": "qx.application", "name": "application"}, "type": "package", "children": [{"type": "classes", "children": [{"attributes": {"isStatic": true, "name": "Standalone", "packageName": "qx.application", "externalRef": true, "childClasses": "qxex.Application", "fullName": "qx.application.Standalone"}, "type": "class"}]}]}, {"attributes": {"packageName": "qx", "fullName": "qx.core", "name": "core"}, "type": "package", "children": [{"type": "classes", "children": [{"attributes": {"isStatic": true, "name": "Object", "packageName": "qx.core", "externalRef": true, "childClasses": "qxex.util.LanguageManager", "fullName": "qx.core.Object"}, "type": "class"}]}]}, {"attributes": {"packageName": "qx", "fullName": "qx.locale", "name": "locale"}, "type": "package", "children": [{"type": "classes", "children": [{"attributes": {"isStatic": true, "name": "MTranslation", "packageName": "qx.locale", "includer": "qxex.ui.table.TableWithModelWidget,qxex.util.LanguageManager", "externalRef": true, "fullName": "qx.locale.MTranslation"}, "type": "class"}]}]}, {"attributes": {"packageName": "qx", "fullName": "qx.ui", "name": "ui"}, "type": "package", "children": [{"type": "packages", "children": [{"attributes": {"packageName": "qx.ui", "fullName": "qx.ui.core", "name": "core"}, "type": "package", "children": [{"type": "classes", "children": [{"attributes": {"isStatic": true, "name": "IMultiSelection", "packageName": "qx.ui.core", "implementations": "qxex.ui.form.MultiSelectBox", "externalRef": true, "fullName": "qx.ui.core.IMultiSelection"}, "type": "class"}, {"attributes": {"isStatic": true, "name": "MExecutable", "packageName": "qx.ui.core", "includer": "qxex.ui.control.TimeChooser", "externalRef": true, "fullName": "qx.ui.core.MExecutable"}, "type": "class"}, {"attributes": {"isStatic": true, "name": "Widget", "packageName": "qx.ui.core", "externalRef": true, "childClasses": "qxex.ui.control.TimeChooser,qxex.ui.table.TableWithModelWidget", "fullName": "qx.ui.core.Widget"}, "type": "class"}]}]}, {"attributes": {"packageName": "qx.ui", "fullName": "qx.ui.form", "name": "form"}, "type": "package", "children": [{"type": "classes", "children": [{"attributes": {"isStatic": true, "name": "AbstractSelectBox", "packageName": "qx.ui.form", "externalRef": true, "childClasses": "qxex.ui.form.AbstractSelectBoxSimpler", "fullName": "qx.ui.form.AbstractSelectBox"}, "type": "class"}, {"attributes": {"isStatic": true, "name": "CheckBox", "packageName": "qx.ui.form", "externalRef": true, "childClasses": "qxex.ui.form.TristateCheckBox", "fullName": "qx.ui.form.CheckBox"}, "type": "class"}, {"attributes": {"isStatic": true, "name": "ComboBox", "packageName": "qx.ui.form", "externalRef": true, "childClasses": "qxex.ui.form.FilterComboBox,qxex.ui.form.MultiLangTextField", "fullName": "qx.ui.form.ComboBox"}, "type": "class"}, {"attributes": {"isStatic": true, "name": "DateField", "packageName": "qx.ui.form", "externalRef": true, "childClasses": "qxex.ui.form.DateField", "fullName": "qx.ui.form.DateField"}, "type": "class"}, {"attributes": {"isStatic": true, "name": "IDateForm", "packageName": "qx.ui.form", "implementations": "qxex.ui.control.TimeChooser", "externalRef": true, "fullName": "qx.ui.form.IDateForm"}, "type": "class"}, {"attributes": {"isStatic": true, "name": "IExecutable", "packageName": "qx.ui.form", "implementations": "qxex.ui.control.TimeChooser", "externalRef": true, "fullName": "qx.ui.form.IExecutable"}, "type": "class"}, {"attributes": {"isStatic": true, "name": "IForm", "packageName": "qx.ui.form", "implementations": "qxex.ui.control.TimeChooser", "externalRef": true, "fullName": "qx.ui.form.IForm"}, "type": "class"}, {"attributes": {"isStatic": true, "name": "IModelSelection", "packageName": "qx.ui.form", "implementations": "qxex.ui.form.MultiSelectBox", "externalRef": true, "fullName": "qx.ui.form.IModelSelection"}, "type": "class"}, {"attributes": {"isStatic": true, "name": "MForm", "packageName": "qx.ui.form", "includer": "qxex.ui.control.TimeChooser", "externalRef": true, "fullName": "qx.ui.form.MForm"}, "type": "class"}, {"attributes": {"isStatic": true, "name": "MModelSelection", "packageName": "qx.ui.form", "includer": "qxex.ui.form.MultiSelectBox", "externalRef": true, "fullName": "qx.ui.form.MModelSelection"}, "type": "class"}, {"attributes": {"isStatic": true, "name": "SelectBox", "packageName": "qx.ui.form", "externalRef": true, "childClasses": "qxex.ui.control.LanguageSelector,qxex.ui.control.ThemeSelector,qxex.ui.form.FilterSelectBox", "fullName": "qx.ui.form.SelectBox"}, "type": "class"}, {"attributes": {"isStatic": true, "name": "Slider", "packageName": "qx.ui.form", "externalRef": true, "childClasses": "qxex.ui.form.KnobIconSlider", "fullName": "qx.ui.form.Slider"}, "type": "class"}]}]}, {"attributes": {"packageName": "qx.ui", "fullName": "qx.ui.table", "name": "table"}, "type": "package", "children": [{"type": "packages", "children": [{"attributes": {"packageName": "qx.ui.table", "fullName": "qx.ui.table.headerrenderer", "name": "headerrenderer"}, "type": "package", "children": [{"type": "classes", "children": [{"attributes": {"isStatic": true, "name": "Default", "packageName": "qx.ui.table.headerrenderer", "externalRef": true, "childClasses": "qxex.ui.table.headerrenderer.FilterAndShiftSortingRenderer", "fullName": "qx.ui.table.headerrenderer.Default"}, "type": "class"}, {"attributes": {"isStatic": true, "name": "HeaderCell", "packageName": "qx.ui.table.headerrenderer", "externalRef": true, "childClasses": "qxex.ui.table.headerrenderer.FilterHeaderCell", "fullName": "qx.ui.table.headerrenderer.HeaderCell"}, "type": "class"}]}]}]}]}, {"attributes": {"packageName": "qx.ui", "fullName": "qx.ui.tree", "name": "tree"}, "type": "package", "children": [{"type": "packages", "children": [{"attributes": {"packageName": "qx.ui.tree", "fullName": "qx.ui.tree.selection", "name": "selection"}, "type": "package", "children": [{"type": "classes", "children": [{"attributes": {"isStatic": true, "name": "SelectionManager", "packageName": "qx.ui.tree.selection", "externalRef": true, "childClasses": "qxex.ui.tree.SelectionManager", "fullName": "qx.ui.tree.selection.SelectionManager"}, "type": "class"}]}]}]}, {"type": "classes", "children": [{"attributes": {"isStatic": true, "name": "Tree", "packageName": "qx.ui.tree", "externalRef": true, "childClasses": "qxex.ui.tree.Tree", "fullName": "qx.ui.tree.Tree"}, "type": "class"}]}]}]}]}]}]}, {"attributes": {"packageName": "", "fullName": "qxex", "hasWarning": true, "name": "qxex"}, "type": "package", "children": [{"type": "packages", "children": [{"attributes": {"packageName": "qxex", "fullName": "qxex.ui", "hasWarning": true, "name": "ui"}, "type": "package", "children": [{"type": "packages", "children": [{"attributes": {"packageName": "qxex.ui", "fullName": "qxex.ui.control", "hasWarning": true, "name": "control"}, "type": "package", "children": [{"type": "classes", "children": [{"attributes": {"name": "LanguageSelector", "hasWarning": true, "packageName": "qxex.ui.control", "externalRef": true, "superClass": "qx.ui.form.SelectBox", "fullName": "qxex.ui.control.LanguageSelector", "type": "class"}, "type": "class"}, {"attributes": {"name": "ThemeSelector", "hasWarning": true, "packageName": "qxex.ui.control", "externalRef": true, "superClass": "qx.ui.form.SelectBox", "fullName": "qxex.ui.control.ThemeSelector", "type": "class"}, "type": "class"}, {"attributes": {"name": "TimeChooser", "hasWarning": true, "packageName": "qxex.ui.control", "mixins": "qx.ui.core.MExecutable,qx.ui.form.MForm", "externalRef": true, "superClass": "qx.ui.core.Widget", "fullName": "qxex.ui.control.TimeChooser", "type": "class", "interfaces": "qx.ui.form.IExecutable,qx.ui.form.IForm,qx.ui.form.IDateForm"}, "type": "class"}]}]}, {"attributes": {"packageName": "qxex.ui", "fullName": "qxex.ui.form", "hasWarning": true, "name": "form"}, "type": "package", "children": [{"type": "classes", "children": [{"attributes": {"isAbstract": true, "name": "AbstractSelectBoxSimpler", "hasWarning": true, "packageName": "qxex.ui.form", "externalRef": true, "superClass": "qx.ui.form.AbstractSelectBox", "childClasses": "qxex.ui.form.MultiSelectBox,qxex.ui.form.TreeSelectBox", "fullName": "qxex.ui.form.AbstractSelectBoxSimpler", "type": "class"}, "type": "class"}, {"attributes": {"name": "DateField", "hasWarning": true, "packageName": "qxex.ui.form", "externalRef": true, "superClass": "qx.ui.form.DateField", "childClasses": "qxex.ui.form.TimeField", "fullName": "qxex.ui.form.DateField", "type": "class"}, "type": "class"}, {"attributes": {"name": "FilterComboBox", "hasWarning": true, "packageName": "qxex.ui.form", "mixins": "qxex.ui.form.MSelectBoxFilter", "externalRef": true, "superClass": "qx.ui.form.ComboBox", "fullName": "qxex.ui.form.FilterComboBox", "type": "class"}, "type": "class"}, {"attributes": {"name": "FilterMultiSelectBox", "hasWarning": true, "packageName": "qxex.ui.form", "mixins": "qxex.ui.form.MSelectBoxFilter", "externalRef": true, "superClass": "qxex.ui.form.MultiSelectBox", "fullName": "qxex.ui.form.FilterMultiSelectBox", "type": "class"}, "type": "class"}, {"attributes": {"name": "FilterSelectBox", "hasWarning": true, "packageName": "qxex.ui.form", "mixins": "qxex.ui.form.MSelectBoxFilter,qxex.ui.form.MSelectBoxSyncListItemStyle", "externalRef": true, "superClass": "qx.ui.form.SelectBox", "fullName": "qxex.ui.form.FilterSelectBox", "type": "class"}, "type": "class"}, {"attributes": {"name": "FilterTreeSelectBox", "hasWarning": true, "packageName": "qxex.ui.form", "externalRef": true, "superClass": "qxex.ui.form.TreeSelectBox", "fullName": "qxex.ui.form.FilterTreeSelectBox", "type": "class"}, "type": "class"}, {"attributes": {"name": "KnobIconSlider", "hasWarning": true, "packageName": "qxex.ui.form", "externalRef": true, "superClass": "qx.ui.form.Slider", "fullName": "qxex.ui.form.KnobIconSlider", "type": "class"}, "type": "class"}, {"attributes": {"name": "MSelectBoxFilter", "hasWarning": true, "packageName": "qxex.ui.form", "includer": "qxex.ui.form.FilterMultiSelectBox,qxex.ui.form.FilterComboBox,qxex.ui.form.FilterSelectBox", "externalRef": true, "fullName": "qxex.ui.form.MSelectBoxFilter", "type": "mixin"}, "type": "class"}, {"attributes": {"name": "MSelectBoxSyncButtonStyle", "hasWarning": true, "packageName": "qxex.ui.form", "includer": "qxex.ui.form.MultiSelectBox", "externalRef": true, "fullName": "qxex.ui.form.MSelectBoxSyncButtonStyle", "type": "mixin"}, "type": "class"}, {"attributes": {"name": "MSelectBoxSyncListItemStyle", "hasWarning": true, "packageName": "qxex.ui.form", "includer": "qxex.ui.form.FilterSelectBox", "externalRef": true, "fullName": "qxex.ui.form.MSelectBoxSyncListItemStyle", "type": "mixin"}, "type": "class"}, {"attributes": {"name": "MultiLangTextField", "hasWarning": true, "packageName": "qxex.ui.form", "externalRef": true, "superClass": "qx.ui.form.ComboBox", "fullName": "qxex.ui.form.MultiLangTextField", "type": "class"}, "type": "class"}, {"attributes": {"name": "MultiSelectBox", "hasWarning": true, "interfaces": "qx.ui.core.IMultiSelection,qx.ui.form.IModelSelection", "mixins": "qx.ui.form.MModelSelection,qxex.ui.form.MSelectBoxSyncButtonStyle", "externalRef": true, "superClass": "qxex.ui.form.AbstractSelectBoxSimpler", "childClasses": "qxex.ui.form.FilterMultiSelectBox", "fullName": "qxex.ui.form.MultiSelectBox", "type": "class", "packageName": "qxex.ui.form"}, "type": "class"}, {"attributes": {"name": "TimeField", "hasWarning": true, "packageName": "qxex.ui.form", "externalRef": true, "superClass": "qxex.ui.form.DateField", "fullName": "qxex.ui.form.TimeField", "type": "class"}, "type": "class"}, {"attributes": {"name": "TreeSelectBox", "hasWarning": true, "packageName": "qxex.ui.form", "externalRef": true, "superClass": "qxex.ui.form.AbstractSelectBoxSimpler", "childClasses": "qxex.ui.form.FilterTreeSelectBox", "fullName": "qxex.ui.form.TreeSelectBox", "type": "class"}, "type": "class"}, {"attributes": {"name": "TristateCheckBox", "hasWarning": true, "packageName": "qxex.ui.form", "externalRef": true, "superClass": "qx.ui.form.CheckBox", "fullName": "qxex.ui.form.TristateCheckBox", "type": "class"}, "type": "class"}]}]}, {"attributes": {"packageName": "qxex.ui", "fullName": "qxex.ui.table", "hasWarning": true, "name": "table"}, "type": "package", "children": [{"type": "classes", "children": [{"attributes": {"name": "TableWithModelWidget", "hasWarning": true, "packageName": "qxex.ui.table", "mixins": "qx.locale.MTranslation", "externalRef": true, "superClass": "qx.ui.core.Widget", "childClasses": "qxex.ui.table.TableWithModelWidgetForTree", "fullName": "qxex.ui.table.TableWithModelWidget", "type": "class"}, "type": "class"}, {"attributes": {"name": "TableWithModelWidgetForTree", "hasWarning": true, "packageName": "qxex.ui.table", "externalRef": true, "superClass": "qxex.ui.table.TableWithModelWidget", "fullName": "qxex.ui.table.TableWithModelWidgetForTree", "type": "class"}, "type": "class"}]}, {"type": "packages", "children": [{"attributes": {"packageName": "qxex.ui.table", "fullName": "qxex.ui.table.headerrenderer", "hasWarning": true, "name": "headerrenderer"}, "type": "package", "children": [{"type": "classes", "children": [{"attributes": {"name": "FilterAndShiftSortingRenderer", "hasWarning": true, "packageName": "qxex.ui.table.headerrenderer", "externalRef": true, "superClass": "qx.ui.table.headerrenderer.Default", "fullName": "qxex.ui.table.headerrenderer.FilterAndShiftSortingRenderer", "type": "class"}, "type": "class"}, {"attributes": {"name": "FilterHeaderCell", "hasWarning": true, "packageName": "qxex.ui.table.headerrenderer", "externalRef": true, "superClass": "qx.ui.table.headerrenderer.HeaderCell", "fullName": "qxex.ui.table.headerrenderer.FilterHeaderCell", "type": "class"}, "type": "class"}]}]}]}]}, {"attributes": {"packageName": "qxex.ui", "fullName": "qxex.ui.tree", "hasWarning": true, "name": "tree"}, "type": "package", "children": [{"type": "classes", "children": [{"attributes": {"hasError": true, "name": "SelectionManager", "hasWarning": true, "packageName": "qxex.ui.tree", "externalRef": true, "superClass": "qx.ui.tree.selection.SelectionManager", "fullName": "qxex.ui.tree.SelectionManager", "type": "class"}, "type": "class"}, {"attributes": {"hasError": true, "name": "Tree", "hasWarning": true, "packageName": "qxex.ui.tree", "externalRef": true, "superClass": "qx.ui.tree.Tree", "fullName": "qxex.ui.tree.Tree", "type": "class"}, "type": "class"}]}]}]}]}, {"attributes": {"packageName": "qxex", "fullName": "qxex.util", "hasWarning": true, "name": "util"}, "type": "package", "children": [{"type": "classes", "children": [{"attributes": {"name": "LanguageManager", "hasWarning": true, "packageName": "qxex.util", "mixins": "qx.locale.MTranslation", "externalRef": true, "superClass": "qx.core.Object", "isSingleton": true, "fullName": "qxex.util.LanguageManager", "type": "class"}, "type": "class"}, {"attributes": {"isStatic": true, "name": "ThemeManager", "hasWarning": true, "packageName": "qxex.util", "hasError": true, "externalRef": true, "fullName": "qxex.util.ThemeManager", "type": "class"}, "type": "class"}]}]}]}, {"type": "classes", "children": [{"attributes": {"name": "Application", "hasWarning": true, "packageName": "qxex", "externalRef": true, "superClass": "qx.application.Standalone", "fullName": "qxex.Application", "type": "class"}, "type": "class"}]}, {"attributes": {"text": "<h3> qxex API Documentation </h3>\n\n<p>Additional <span class=\"caps\">GUI</span> widgets and other stuff for qooxdoo apps.</p>"}, "type": "desc"}]}]}]}